contact_person_profile_csv_imp_local/CSVToContactPersonProfile.py
contact_person_profile_csv_imp_local/__init__.py
contact_person_profile_csv_imp_local/contact_person_profile_csv_imp_local_constants.py
contact_person_profile_csv_imp_local-0.0.55.dist-info/METADATA
contact_person_profile_csv_imp_local-0.0.55.dist-info/WHEEL
contact_person_profile_csv_imp_local-0.0.55.dist-info/top_level.txt
contact_person_profile_csv_imp_local-0.0.55.dist-info/RECORD
