Metadata-Version: 2.4
Name: contact-person-profile-csv-imp-local
Version: 0.0.55
Summary: PyPI Package for Circles CSVToContactPersonProfile-local Local/Remote Python
Home-page: https://github.com/circles-zone/contact-person-profile-csv-imp-local-python-package
Author: Circles
Author-email: info@circles.ai
Classifier: Programming Language :: Python :: 3
Classifier: Operating System :: OS Independent
Requires-Dist: contact-local>=0.0.48
Requires-Dist: logger-local>=0.0.135
Requires-Dist: database-mysql-local>=0.1.1
Requires-Dist: user-context-remote>=0.0.77
Requires-Dist: contact-email-address-local>=0.0.40.1234
Requires-Dist: contact-group-local>=0.0.68
Requires-Dist: contact-location-local>=0.0.14
Requires-Dist: contact-notes-local>=0.0.33
Requires-Dist: contact-persons-local>=0.0.8
Requires-Dist: contact-phone-local>=0.0.12
Requires-Dist: contact-profile-local>=0.0.7
Requires-Dist: contact-user-external-local>=0.0.13
Requires-Dist: importer-local>=0.0.54
Requires-Dist: internet-domain-local>=0.0.8
Requires-Dist: location-local>=0.0.104
Requires-Dist: organization-profile-local>=0.0.4
Requires-Dist: organizations-local>=0.0.14
Requires-Dist: python-sdk-remote>=0.0.93
Requires-Dist: url-remote>=0.0.91
Requires-Dist: user-external-local>=0.0.114
Requires-Dist: chardet>=5.2.0
Dynamic: author
Dynamic: author-email
Dynamic: classifier
Dynamic: description
Dynamic: description-content-type
Dynamic: home-page
Dynamic: requires-dist
Dynamic: summary
